{
  "our_id": "10074",
  "epg": [
    {
      "id": 19525327669,
      "epg_id": 195,
      "timestart": 1756255500,
      "timestop": 1756260000,
      "title": "Таинственный остров",
      "desc": "Во время Гражданской войны в Америке пятеро пленных бегут из осажденного Ричмонда на воздушном шаре. Ураган уносит их на необитаемый остров. Тысячи миль отделяют колонистов от обитаемой земли, а все их имущество - нож, часы и записная книжка…",
      "cdnvideo": 0,
      "rating": 16,
      "video_url": "",
      "vod_id": 0,
      "sub_title": "",
      "season": 0,
      "category": [
        "Х/ф",
        "Приключения",
        "Фантастика"
      ],
      "genre": null,
      "mskdatetimestart": "2025-08-27 03:45:00",
      "usrdatetimestart": "2025-08-27 03:45:00",
      "ddiff": 1,
      "preview": ""
    },
    {
      "id": 19525327795,
      "epg_id": 195,
      "timestart": 1756305900,
      "timestop": 1756310400,
      "title": "Таинственный остров",
      "desc": "Во время Гражданской войны в Америке пятеро пленных бегут из осажденного Ричмонда на воздушном шаре. Ураган уносит их на необитаемый остров. Тысячи миль отделяют колонистов от обитаемой земли, а все их имущество - нож, часы и записная книжка…",
      "cdnvideo": 0,
      "rating": 16,
      "video_url": "",
      "vod_id": 0,
      "sub_title": "",
      "season": 0,
      "category": [
        "Х/ф",
        "Приключения",
        "Фантастика"
      ],
      "genre": null,
      "mskdatetimestart": "2025-08-27 17:45:00",
      "usrdatetimestart": "2025-08-27 17:45:00",
      "ddiff": 1,
      "preview": ""
    },
    {
      "id": 19525327914,
      "epg_id": 195,
      "timestart": 1756341900,
      "timestop": 1756346400,
      "title": "Новый дом",
      "desc": "Председатель колхоза Мария Степановна, бывшая партизанка, углядев пустующий участок, решает расширить за счёт него посевные площади. Этот же участок приглянулся председателю соседнего колхоза - старому партизану Вишняку",
      "cdnvideo": 0,
      "rating": 16,
      "video_url": "",
      "vod_id": 0,
      "sub_title": "",
      "season": 0,
      "category": [
        "Х/ф",
        "Комедия"
      ],
      "genre": null,
      "mskdatetimestart": "2025-08-28 03:45:00",
      "usrdatetimestart": "2025-08-28 03:45:00",
      "ddiff": 2,
      "preview": ""
    },
    {
      "id": 19525328040,
      "epg_id": 195,
      "timestart": 1756392300,
      "timestop": 1756396800,
      "title": "Новый дом",
      "desc": "Председатель колхоза Мария Степановна, бывшая партизанка, углядев пустующий участок, решает расширить за счёт него посевные площади. Этот же участок приглянулся председателю соседнего колхоза - старому партизану Вишняку",
      "cdnvideo": 0,
      "rating": 16,
      "video_url": "",
      "vod_id": 0,
      "sub_title": "",
      "season": 0,
      "category": [
        "Х/ф",
        "Комедия"
      ],
      "genre": null,
      "mskdatetimestart": "2025-08-28 17:45:00",
      "usrdatetimestart": "2025-08-28 17:45:00",
      "ddiff": 2,
      "preview": ""
    },
    {
      "id": 19525328159,
      "epg_id": 195,
      "timestart": 1756428300,
      "timestop": 1756432800,
      "title": "Сын полка",
      "desc": "Когда в бою с прорвавшимися немецкими танками гибнет расчёт батареи, Ваню отправляют в Суворовское училище, воспитанники которого участвуют в военном параде на Красной площади",
      "cdnvideo": 0,
      "rating": 16,
      "video_url": "",
      "vod_id": 0,
      "sub_title": "",
      "season": 0,
      "category": [
        "Х/ф",
        "Военный",
        "Драма"
      ],
      "genre": null,
      "mskdatetimestart": "2025-08-29 03:45:00",
      "usrdatetimestart": "2025-08-29 03:45:00",
      "ddiff": 3,
      "preview": ""
    },
    {
      "id": 19525328285,
      "epg_id": 195,
      "timestart": 1756478700,
      "timestop": 1756483200,
      "title": "Сын полка",
      "desc": "Когда в бою с прорвавшимися немецкими танками гибнет расчёт батареи, Ваню отправляют в Суворовское училище, воспитанники которого участвуют в военном параде на Красной площади",
      "cdnvideo": 0,
      "rating": 16,
      "video_url": "",
      "vod_id": 0,
      "sub_title": "",
      "season": 0,
      "category": [
        "Х/ф",
        "Военный",
        "Драма"
      ],
      "genre": null,
      "mskdatetimestart": "2025-08-29 17:45:00",
      "usrdatetimestart": "2025-08-29 17:45:00",
      "ddiff": 3,
      "preview": ""
    },
    {
      "id": 19525328404,
      "epg_id": 195,
      "timestart": 1756514700,
      "timestop": 1756519200,
      "title": "Жила-была девочка",
      "desc": "Голод, холод, путешествия через вымерзший город к Неве с санками за водой, смерть матери, ранение - все это выпало на долю детей, перенесших наравне со взрослыми все тяготы войны",
      "cdnvideo": 0,
      "rating": 16,
      "video_url": "",
      "vod_id": 0,
      "sub_title": "",
      "season": 0,
      "category": [
        "Х/ф",
        "Драма",
        "Военный"
      ],
      "genre": null,
      "mskdatetimestart": "2025-08-30 03:45:00",
      "usrdatetimestart": "2025-08-30 03:45:00",
      "ddiff": 4,
      "preview": ""
    },
    {
      "id": 19525328516,
      "epg_id": 195,
      "timestart": 1756565100,
      "timestop": 1756569600,
      "title": "Жила-была девочка",
      "desc": "Голод, холод, путешествия через вымерзший город к Неве с санками за водой, смерть матери, ранение - все это выпало на долю детей, перенесших наравне со взрослыми все тяготы войны",
      "cdnvideo": 0,
      "rating": 16,
      "video_url": "",
      "vod_id": 0,
      "sub_title": "",
      "season": 0,
      "category": [
        "Х/ф",
        "Драма",
        "Военный"
      ],
      "genre": null,
      "mskdatetimestart": "2025-08-30 17:45:00",
      "usrdatetimestart": "2025-08-30 17:45:00",
      "ddiff": 4,
      "preview": ""
    }
  ]
}